zetaSeq/__init__.py
zetaSeq/amplicon.py
zetaSeq/io.py
zetaSeq/rarefy.py
zetaSeq/util.py
zetaSeq/zs.py
zetaSeq-0.0.10.dist-info/LICENSE
zetaSeq-0.0.10.dist-info/METADATA
zetaSeq-0.0.10.dist-info/WHEEL
zetaSeq-0.0.10.dist-info/entry_points.txt
zetaSeq-0.0.10.dist-info/top_level.txt
zetaSeq-0.0.10.dist-info/RECORD
